snax/__init__.py
snax/column_like.py
snax/entity.py
snax/feature.py
snax/feature_store.py
snax/feature_view.py
snax/repo_contents.py
snax/type_casting.py
snax/utils.py
snax/value_type.py
snax/data/game.csv
snax/data/users_with_nas.csv
snax/data/winequality.csv
snax/data_sources/__init__.py
snax/data_sources/_oracle_special_keywords.py
snax/data_sources/_oracle_utils.py
snax/data_sources/csv_data_source.py
snax/data_sources/data_source_base.py
snax/data_sources/in_memory_data_source.py
snax/data_sources/oracle_data_source.py
snax/data_sources/examples/__init__.py
snax/data_sources/examples/csv.py
snax/data_sources/examples/in_memory.py
snax/data_sources/examples/oracle.py
snax/example_feature_repos/__init__.py
snax/example_feature_repos/sports_feature_repo/__init__.py
snax/example_feature_repos/sports_feature_repo/nhl_games.py
snax/example_feature_repos/users_with_nas_feature_repo/__init__.py
snax/example_feature_repos/users_with_nas_feature_repo/users_with_nas.py
snax/example_feature_repos/winequality_feature_repo/__init__.py
snax/example_feature_repos/winequality_feature_repo/winequality.py
tests/__init__.py
tests/test_column_like.py
tests/test_feature_store.py
tests/test_feature_view.py
tests/test_oracle_utils.py
tests/test_repo_contents.py
tests/test_type_casting.py
tests/test_utils.py
tests/data_sources/__init__.py
tests/data_sources/test_csv_data_source.py
tests/data_sources/test_data_source.py
tests/data_sources/test_in_memory_data_source.py
tests/data_sources/test_oracle_data_source.py
snax-0.1.0.dist-info/METADATA
snax-0.1.0.dist-info/WHEEL
snax-0.1.0.dist-info/top_level.txt
snax-0.1.0.dist-info/RECORD
