Metadata-Version: 2.1
Name: snax
Version: 0.1.0
Summary: The truly lightweight feature store
Author: Josef Ondrej
Author-email: josef.ondrej@outlook.com
Requires-Dist: pandas (>=1.4.0)
Requires-Dist: sqlalchemy (>=1.4.0)
